stwex/__init__.py
stwex/stwex.py
stwex/images/logo.png
stwex/images/logoStwex.png
stwex/images/stwex.png
StwEx-0.1.1.dist-info/LICENSE.txt
StwEx-0.1.1.dist-info/METADATA
StwEx-0.1.1.dist-info/WHEEL
StwEx-0.1.1.dist-info/entry_points.txt
StwEx-0.1.1.dist-info/top_level.txt
StwEx-0.1.1.dist-info/RECORD
