Metadata-Version: 2.1
Name: StwEx
Version: 0.1.1
Summary: Controlar cualquier aplicación desde un icono con menú y submenus en el systray
Home-page: https://gitlab.com/germansg/stwex
Author: German Sanchez Gutierrez
Author-email: gsgsoftgroup@gmail.com
License: GNU General Public License v3 (GPLv3)
Platform: Linux
Classifier: Programming Language :: Python :: 3
Classifier: License :: OSI Approved :: GNU General Public License v3 (GPLv3)
Classifier: Operating System :: POSIX :: Linux
Requires-Python: >=3.6
Requires-Dist: wxPython (>=4.1.1)
